{
	"class" : {
		"initialize" : "svp 5/6/2003 14:51",
		"on:" : "gc 8/29/2008 17:15",
		"on:named:" : "gc 9/2/2008 23:35",
		"serviceOnPort:" : "gc 7/8/2005 09:45",
		"serviceOnPort:ifAbsent:" : "gc 7/8/2005 09:45",
		"services" : "gk 12/6/2005 23:07",
		"startOn:" : "svp 1/17/2003 14:16",
		"startOn:named:" : "gc 9/2/2008 23:36" },
	"instance" : {
		"address" : "gc 8/29/2008 17:27",
		"address:" : "gc 8/29/2008 17:27",
		"assignPort" : "svp 1/21/2003 14:37",
		"initializeOnPort:address:priority:" : "gc 8/29/2008 15:48",
		"initializeOnPort:priority:" : "svp 5/6/2003 14:54",
		"portNumber" : "svp 1/17/2003 16:14",
		"portNumber:" : "svp 5/6/2003 14:53",
		"prepareForStartup" : "lr 10/26/2010 21:34",
		"printOn:" : "lr 10/12/2010 15:27",
		"runWhile:" : "gc 8/29/2008 15:47",
		"serve:" : "svp 8/20/2003 00:30",
		"start" : "svp 4/25/2003 16:27",
		"startOn:" : "svp 1/17/2003 16:14",
		"unassignPort" : "svp 1/17/2003 15:26",
		"value:" : "lr 10/12/2010 15:38",
		"verifyPortAvailability:" : "svp 1/21/2003 14:37" } }
